conda_app-0.6.0.dist-info/METADATA
conda_app-0.6.0.dist-info/WHEEL
conda_app-0.6.0.dist-info/entry_points.txt
conda_app-0.6.0.dist-info/licenses/LICENSE.txt
conda_app.py
conda_app-0.6.0.dist-info/RECORD
