Metadata-Version: 2.1
Name: conda-app
Version: 0.6.0
Summary: Install applications with conda
Keywords: conda,packaging
Author: Pierre Augier
License: BSD
Classifier: License :: OSI Approved :: BSD License
Classifier: Programming Language :: Python :: 3
Classifier: Programming Language :: Python :: 3.10
Classifier: Programming Language :: Python :: 3.11
Classifier: Programming Language :: Python :: 3.12
Classifier: Programming Language :: Python :: 3.13
Project-URL: Homepage, https://foss.heptapod.net/fluiddyn/conda-app/
Requires-Python: >=3.10
Requires-Dist: click
Requires-Dist: userpath>=1.9.2
